a2y_mew.cp312-win_amd64.pyd
a2y_mew-0.9.10.dist-info/LICENSE
a2y_mew-0.9.10.dist-info/METADATA
a2y_mew-0.9.10.dist-info/WHEEL
a2y_mew-0.9.10.dist-info/top_level.txt
a2y_mew-0.9.10.dist-info/RECORD
