Metadata-Version: 2.2
Name: a2y_mew
Version: 0.9.10
Summary: A module that implements improved Mewtocol.
Home-page: http://www.kersci.com/a2y/mew.html
Author: Yu Han
Author-email: hanjunyu@163.com
License: Private
Platform: Windows
Platform: Linux
Classifier: Development Status :: 4 - Beta
Classifier: Intended Audience :: Developers
Classifier: License :: Free For Educational Use
Classifier: Programming Language :: Python :: 3.6
Classifier: Operating System :: Microsoft :: Windows :: Windows 10
Classifier: Operating System :: POSIX :: Linux
License-File: LICENSE
Requires-Dist: pyserial>=3.0
Requires-Dist: a2y-kcom>=0.8.4
Dynamic: author
Dynamic: author-email
Dynamic: classifier
Dynamic: description
Dynamic: description-content-type
Dynamic: home-page
Dynamic: license
Dynamic: platform
Dynamic: requires-dist
Dynamic: summary
